secondstotext/__init__.py
secondstotext/main.py
secondstotext-1.0.4.dist-info/LICENSE
secondstotext-1.0.4.dist-info/METADATA
secondstotext-1.0.4.dist-info/WHEEL
secondstotext-1.0.4.dist-info/top_level.txt
secondstotext-1.0.4.dist-info/RECORD
